microvm_client/__init__.py
microvm_client/client.py
microvm_client/exceptions.py
microvm_client/models.py
py_microvm-1.0.1.dist-info/METADATA
py_microvm-1.0.1.dist-info/WHEEL
py_microvm-1.0.1.dist-info/licenses/LICENSE
py_microvm-1.0.1.dist-info/RECORD
