Metadata-Version: 2.4
Name: py-microvm
Version: 1.0.1
Summary: Lightweight Python client for MicroVM Sandbox with enterprise security
Project-URL: Homepage, https://github.com/CodeDuet/codeduet-microvm-ai-agent-sandbox
Project-URL: Documentation, https://github.com/CodeDuet/codeduet-microvm-ai-agent-sandbox/tree/main/docs
Project-URL: Repository, https://github.com/CodeDuet/codeduet-microvm-ai-agent-sandbox
Project-URL: Changelog, https://github.com/CodeDuet/codeduet-microvm-ai-agent-sandbox/blob/main/py-microvm/CHANGELOG.md
Project-URL: Bug Tracker, https://github.com/CodeDuet/codeduet-microvm-ai-agent-sandbox/issues
Author-email: CodeDuet MicroVM Sandbox Team <support@microvm-sandbox.dev>
Maintainer-email: CodeDuet MicroVM Sandbox Team <support@microvm-sandbox.dev>
License-Expression: MIT
License-File: LICENSE
Classifier: Development Status :: 5 - Production/Stable
Classifier: Environment :: Console
Classifier: Framework :: AsyncIO
Classifier: Intended Audience :: Developers
Classifier: License :: OSI Approved :: MIT License
Classifier: Operating System :: OS Independent
Classifier: Programming Language :: Python :: 3
Classifier: Programming Language :: Python :: 3.9
Classifier: Programming Language :: Python :: 3.10
Classifier: Programming Language :: Python :: 3.11
Classifier: Programming Language :: Python :: 3.12
Classifier: Topic :: Software Development :: Libraries :: Python Modules
Classifier: Topic :: System :: Systems Administration
Classifier: Typing :: Typed
Requires-Python: >=3.9
Requires-Dist: httpx<0.26.0,>=0.25.0
Requires-Dist: pydantic<3.0.0,>=2.4.0
Provides-Extra: dev
Requires-Dist: bandit>=1.7.0; extra == 'dev'
Requires-Dist: black>=23.0.0; extra == 'dev'
Requires-Dist: mypy>=1.5.0; extra == 'dev'
Requires-Dist: pytest-asyncio>=0.21.0; extra == 'dev'
Requires-Dist: pytest-cov>=4.0.0; extra == 'dev'
Requires-Dist: pytest>=7.0.0; extra == 'dev'
Requires-Dist: ruff>=0.1.0; extra == 'dev'
Requires-Dist: safety>=2.3.0; extra == 'dev'
